glato/__init__.py
glato/main.py
glato/attack/__init__.py
glato/attack/attack.py
glato/attack/cicd_attack.py
glato/cli/__init__.py
glato/cli/cli.py
glato/enumerate/__init__.py
glato/enumerate/enumerate.py
glato/gitlab/__init__.py
glato/gitlab/api.py
glato/gitlab/secrets.py
glato/gitlab/workflow_parser.py
glato/models/__init__.py
glato/models/group.py
glato/models/project.py
glato/models/runner.py
glato/models/secure_file.py
glato/models/user.py
glato/models/variable.py
glato/services/__init__.py
glato/services/project.py
glato/templates/cookies.json
glato/util/__init__.py
glato/util/cookie_config.py
glato/util/decorators.py
praetorian_glato-1.0.0b5.dist-info/licenses/LICENSE
praetorian_glato-1.0.0b5.dist-info/METADATA
praetorian_glato-1.0.0b5.dist-info/WHEEL
praetorian_glato-1.0.0b5.dist-info/entry_points.txt
praetorian_glato-1.0.0b5.dist-info/top_level.txt
praetorian_glato-1.0.0b5.dist-info/RECORD
